cnpt/__init__.py
cnpt/example.py
cnpt/extractor.py
cnpt/injector.py
cnpt/pos_tag.py
cnpt/rule.py
cnpt_leos-0.1.1.dist-info/METADATA
cnpt_leos-0.1.1.dist-info/RECORD
cnpt_leos-0.1.1.dist-info/WHEEL
cnpt_leos-0.1.1.dist-info/top_level.txt
