Metadata-Version: 2.1
Name: cnpt-leos
Version: 0.1.1
Summary: Custom NLTK part of speech tagger
Home-page: UNKNOWN
Author: Dmitry Obukhov
Author-email: bstodin@gmail.com
License: UNKNOWN
Platform: UNKNOWN
Classifier: Programming Language :: Python :: 3
Classifier: License :: OSI Approved :: MIT License
Classifier: Operating System :: OS Independent
